adafruit_circuitpython_radial_controller-1.0.17.dist-info/licenses/LICENSE
adafruit_radial_controller/__init__.py
adafruit_radial_controller/device.py
adafruit_circuitpython_radial_controller-1.0.17.dist-info/METADATA
adafruit_circuitpython_radial_controller-1.0.17.dist-info/WHEEL
adafruit_circuitpython_radial_controller-1.0.17.dist-info/top_level.txt
adafruit_circuitpython_radial_controller-1.0.17.dist-info/RECORD
