Metadata-Version: 2.4
Name: adafruit-circuitpython-radial-controller
Version: 1.0.17
Summary: HID Radial Controller device helper library
Author-email: Adafruit Industries <circuitpython@adafruit.com>
License: MIT
Project-URL: Homepage, https://github.com/adafruit/Adafruit_CircuitPython_Radial_Controller.git
Keywords: adafruit,blinka,circuitpython,micropython,radial_controller,HID,radial,controller
Classifier: Intended Audience :: Developers
Classifier: Topic :: Software Development :: Libraries
Classifier: Topic :: Software Development :: Embedded Systems
Classifier: Topic :: System :: Hardware
Classifier: License :: OSI Approved :: MIT License
Classifier: Programming Language :: Python :: 3
License-File: LICENSE
Requires-Dist: Adafruit-Blinka
Requires-Dist: adafruit-circuitpython-hid
Provides-Extra: optional
Dynamic: license-file
